contextfun/__init__.py
contextfun/main.py
contextfun-0.7.0.dist-info/LICENSE
contextfun-0.7.0.dist-info/METADATA
contextfun-0.7.0.dist-info/WHEEL
contextfun-0.7.0.dist-info/top_level.txt
contextfun-0.7.0.dist-info/RECORD
