Metadata-Version: 2.1
Name: contextfun
Version: 0.7.0
Summary: context based filtering and mapping
Home-page: https://github.com/mittelholcz/contextfun
Author: mittelholcz
Author-email: dev.mittelholcz@gmail.com
License: MIT
Platform: UNKNOWN
Classifier: License :: OSI Approved :: MIT License
Classifier: Operating System :: OS Independent
Classifier: Programming Language :: Python :: 3
Classifier: Programming Language :: Python :: 3.5
Classifier: Programming Language :: Python :: 3.6
Classifier: Programming Language :: Python :: 3.7
